docs/source/conf.py
smoother/__init__.py
smoother/losses.py
smoother/utils.py
smoother/visualization.py
smoother/weights.py
smoother/models/__init__.py
smoother/models/deconv.py
smoother/models/impute.py
smoother/models/reduction/__init__.py
smoother/models/reduction/_spae.py
smoother/models/reduction/_spanvi.py
smoother/models/reduction/_spmultivi.py
smoother/models/reduction/_sppca.py
smoother/models/reduction/_spvae.py
smoother/models/reduction/_utils.py
smoother/simulation/__init__.py
smoother/simulation/gp.py
smoother/simulation/histology.py
smoother/simulation/utils.py
smoother_omics-1.1.0.dist-info/licenses/LICENSE
smoother_omics-1.1.0.dist-info/METADATA
smoother_omics-1.1.0.dist-info/WHEEL
smoother_omics-1.1.0.dist-info/top_level.txt
smoother_omics-1.1.0.dist-info/RECORD
