Metadata-Version: 2.4
Name: smoother-omics
Version: 1.1.0
Summary: Modular loss of spatial dependency for spatial omics data
Author: Jiayu Su
License: BSD 3-Clause License
Project-URL: repository, https://github.com/JiayuSuPKU/Smoother
Requires-Python: <4,>=3.11
License-File: LICENSE
Requires-Dist: torch
Requires-Dist: scipy
Requires-Dist: scikit-learn
Requires-Dist: pandas
Requires-Dist: tqdm
Provides-Extra: plot
Requires-Dist: plotnine; extra == "plot"
Requires-Dist: matplotlib; extra == "plot"
Requires-Dist: seaborn; extra == "plot"
Requires-Dist: scikit-bio; extra == "plot"
Provides-Extra: cvxpy
Requires-Dist: cvxpy>=1.7.3; extra == "cvxpy"
Requires-Dist: torch>=2.8.0; extra == "cvxpy"
Provides-Extra: scvi
Requires-Dist: scvi-tools>=1.4.0; extra == "scvi"
Requires-Dist: jax>=0.7.2; extra == "scvi"
Requires-Dist: torch>=2.8.0; extra == "scvi"
Provides-Extra: full
Requires-Dist: smoother-omics[cvxpy]; extra == "full"
Requires-Dist: smoother-omics[scvi]; extra == "full"
Requires-Dist: smoother-omics[plot]; extra == "full"
Dynamic: license-file
